Workbook

Sheet Monthly Target Tracker
A1: SKIL LIFESTYLE LLP — AJANTA SHOES TARGET & INCENTIVE TRACKER (FY 2026–27)
A2: Annual Target: Rs 1.20 Crore (Basic) | Monthly Target: Rs 10.00 Lakhs (Basic) | Agreement Period: Aug 2026 to Jul 2027
A4: Month | B4: Quarter | C4: Monthly Target (Rs) | D4: Actual Inward Basic (Rs) | E4: Achievement % | F4: Target Status | G4: Monthly Bonus 3% (Rs) | H4: Cash Discount 3% (Rs) | I4: Retail Scheme 3.78% (Rs) | J4: Special / Promo Schemes (Rs) | K4: Total Entitled Basic (Rs) | L4: IGST 5% on Credit Note (Rs) | M4: Gross Credit Note Entitled (Rs) | N4: Credit Note Received (Rs) | O4: Pending Claim / Variance (Rs)
A5: Aug-2026 | B5: Q2 | C5: 1000000 | D5: =SUMIFS('Inward Bill Quick-Log'!G:G, 'Inward Bill Quick-Log'!E:E, "Aug-2026", 'Inward Bill Quick-Log'!C:C, "*Ajanta*") | E5: =IF(C5>0, D5/C5, 0) | F5: =IF(D5=0, "Not Started", IF(E5>=0.99, "Target Met", "Shortfall")) | G5: =IF(E5>=0.99, D5*0.03, 0) | H5: =D5*0.03 | I5: =D5*0.0378 | J5: 28500.95 | K5: =G5+H5+I5+J5 | L5: =K5*0.05 | M5: =K5+L5 | N5: =SUMIFS('Ajanta Credit Notes Log'!G:G, 'Ajanta Credit Notes Log'!B:B, "Aug-2026") | O5: =M5-N5
A6: Sep-2026 | B6: Q2 | C6: 1000000 | D6: =SUMIFS('Inward Bill Quick-Log'!G:G, 'Inward Bill Quick-Log'!E:E, "Sep-2026", 'Inward Bill Quick-Log'!C:C, "*Ajanta*") | E6: =IF(C6>0, D6/C6, 0) | F6: =IF(D6=0, "Not Started", IF(E6>=0.99, "Target Met", "Shortfall")) | G6: =IF(E6>=0.99, D6*0.03, 0) | H6: =D6*0.03 | I6: =D6*0.0378 | J6: 26180 | K6: =G6+H6+I6+J6 | L6: =K6*0.05 | M6: =K6+L6 | N6: =SUMIFS('Ajanta Credit Notes Log'!G:G, 'Ajanta Credit Notes Log'!B:B, "Sep-2026") | O6: =M6-N6
A7: Oct-2026 | B7: Q3 | C7: 1000000 | D7: =SUMIFS('Inward Bill Quick-Log'!G:G, 'Inward Bill Quick-Log'!E:E, "Oct-2026", 'Inward Bill Quick-Log'!C:C, "*Ajanta*") | E7: =IF(C7>0, D7/C7, 0) | F7: =IF(D7=0, "Not Started", IF(E7>=0.99, "Target Met", "Shortfall")) | G7: =IF(E7>=0.99, D7*0.03, 0) | H7: =D7*0.03 | I7: =D7*0.0378 | J7: 0 | K7: =G7+H7+I7+J7 | L7: =K7*0.05 | M7: =K7+L7 | N7: =SUMIFS('Ajanta Credit Notes Log'!G:G, 'Ajanta Credit Notes Log'!B:B, "Oct-2026") | O7: =M7-N7
A8: Nov-2026 | B8: Q3 | C8: 1000000 | D8: =SUMIFS('Inward Bill Quick-Log'!G:G, 'Inward Bill Quick-Log'!E:E, "Nov-2026", 'Inward Bill Quick-Log'!C:C, "*Ajanta*") | E8: =IF(C8>0, D8/C8, 0) | F8: =IF(D8=0, "Not Started", IF(E8>=0.99, "Target Met", "Shortfall")) | G8: =IF(E8>=0.99, D8*0.03, 0) | H8: =D8*0.03 | I8: =D8*0.0378 | J8: 0 | K8: =G8+H8+I8+J8 | L8: =K8*0.05 | M8: =K8+L8 | N8: =SUMIFS('Ajanta Credit Notes Log'!G:G, 'Ajanta Credit Notes Log'!B:B, "Nov-2026") | O8: =M8-N8
A9: Dec-2026 | B9: Q3 | C9: 1000000 | D9: =SUMIFS('Inward Bill Quick-Log'!G:G, 'Inward Bill Quick-Log'!E:E, "Dec-2026", 'Inward Bill Quick-Log'!C:C, "*Ajanta*") | E9: =IF(C9>0, D9/C9, 0) | F9: =IF(D9=0, "Not Started", IF(E9>=0.99, "Target Met", "Shortfall")) | G9: =IF(E9>=0.99, D9*0.03, 0) | H9: =D9*0.03 | I9: =D9*0.0378 | J9: 0 | K9: =G9+H9+I9+J9 | L9: =K9*0.05 | M9: =K9+L9 | N9: =SUMIFS('Ajanta Credit Notes Log'!G:G, 'Ajanta Credit Notes Log'!B:B, "Dec-2026") | O9: =M9-N9
A10: Jan-2027 | B10: Q4 | C10: 1000000 | D10: =SUMIFS('Inward Bill Quick-Log'!G:G, 'Inward Bill Quick-Log'!E:E, "Jan-2027", 'Inward Bill Quick-Log'!C:C, "*Ajanta*") | E10: =IF(C10>0, D10/C10, 0) | F10: =IF(D10=0, "Not Started", IF(E10>=0.99, "Target Met", "Shortfall")) | G10: =IF(E10>=0.99, D10*0.03, 0) | H10: =D10*0.03 | I10: =D10*0.0378 | J10: 0 | K10: =G10+H10+I10+J10 | L10: =K10*0.05 | M10: =K10+L10 | N10: =SUMIFS('Ajanta Credit Notes Log'!G:G, 'Ajanta Credit Notes Log'!B:B, "Jan-2027") | O10: =M10-N10
A11: Feb-2027 | B11: Q4 | C11: 1000000 | D11: =SUMIFS('Inward Bill Quick-Log'!G:G, 'Inward Bill Quick-Log'!E:E, "Feb-2027", 'Inward Bill Quick-Log'!C:C, "*Ajanta*") | E11: =IF(C11>0, D11/C11, 0) | F11: =IF(D11=0, "Not Started", IF(E11>=0.99, "Target Met", "Shortfall")) | G11: =IF(E11>=0.99, D11*0.03, 0) | H11: =D11*0.03 | I11: =D11*0.0378 | J11: 0 | K11: =G11+H11+I11+J11 | L11: =K11*0.05 | M11: =K11+L11 | N11: =SUMIFS('Ajanta Credit Notes Log'!G:G, 'Ajanta Credit Notes Log'!B:B, "Feb-2027") | O11: =M11-N11
A12: Mar-2027 | B12: Q4 | C12: 1000000 | D12: =SUMIFS('Inward Bill Quick-Log'!G:G, 'Inward Bill Quick-Log'!E:E, "Mar-2027", 'Inward Bill Quick-Log'!C:C, "*Ajanta*") | E12: =IF(C12>0, D12/C12, 0) | F12: =IF(D12=0, "Not Started", IF(E12>=0.99, "Target Met", "Shortfall")) | G12: =IF(E12>=0.99, D12*0.03, 0) | H12: =D12*0.03 | I12: =D12*0.0378 | J12: 0 | K12: =G12+H12+I12+J12 | L12: =K12*0.05 | M12: =K12+L12 | N12: =SUMIFS('Ajanta Credit Notes Log'!G:G, 'Ajanta Credit Notes Log'!B:B, "Mar-2027") | O12: =M12-N12
A13: Apr-2027 | B13: Q1 | C13: 1000000 | D13: =SUMIFS('Inward Bill Quick-Log'!G:G, 'Inward Bill Quick-Log'!E:E, "Apr-2027", 'Inward Bill Quick-Log'!C:C, "*Ajanta*") | E13: =IF(C13>0, D13/C13, 0) | F13: =IF(D13=0, "Not Started", IF(E13>=0.99, "Target Met", "Shortfall")) | G13: =IF(E13>=0.99, D13*0.03, 0) | H13: =D13*0.03 | I13: =D13*0.0378 | J13: 0 | K13: =G13+H13+I13+J13 | L13: =K13*0.05 | M13: =K13+L13 | N13: =SUMIFS('Ajanta Credit Notes Log'!G:G, 'Ajanta Credit Notes Log'!B:B, "Apr-2027") | O13: =M13-N13
A14: May-2027 | B14: Q1 | C14: 1000000 | D14: =SUMIFS('Inward Bill Quick-Log'!G:G, 'Inward Bill Quick-Log'!E:E, "May-2027", 'Inward Bill Quick-Log'!C:C, "*Ajanta*") | E14: =IF(C14>0, D14/C14, 0) | F14: =IF(D14=0, "Not Started", IF(E14>=0.99, "Target Met", "Shortfall")) | G14: =IF(E14>=0.99, D14*0.03, 0) | H14: =D14*0.03 | I14: =D14*0.0378 | J14: 0 | K14: =G14+H14+I14+J14 | L14: =K14*0.05 | M14: =K14+L14 | N14: =SUMIFS('Ajanta Credit Notes Log'!G:G, 'Ajanta Credit Notes Log'!B:B, "May-2027") | O14: =M14-N14
A15: Jun-2027 | B15: Q1 | C15: 1000000 | D15: =SUMIFS('Inward Bill Quick-Log'!G:G, 'Inward Bill Quick-Log'!E:E, "Jun-2027", 'Inward Bill Quick-Log'!C:C, "*Ajanta*") | E15: =IF(C15>0, D15/C15, 0) | F15: =IF(D15=0, "Not Started", IF(E15>=0.99, "Target Met", "Shortfall")) | G15: =IF(E15>=0.99, D15*0.03, 0) | H15: =D15*0.03 | I15: =D15*0.0378 | J15: 0 | K15: =G15+H15+I15+J15 | L15: =K15*0.05 | M15: =K15+L15 | N15: =SUMIFS('Ajanta Credit Notes Log'!G:G, 'Ajanta Credit Notes Log'!B:B, "Jun-2027") | O15: =M15-N15
A16: Jul-2027 | B16: Q1 | C16: 1000000 | D16: =SUMIFS('Inward Bill Quick-Log'!G:G, 'Inward Bill Quick-Log'!E:E, "Jul-2027", 'Inward Bill Quick-Log'!C:C, "*Ajanta*") | E16: =IF(C16>0, D16/C16, 0) | F16: =IF(D16=0, "Not Started", IF(E16>=0.99, "Target Met", "Shortfall")) | G16: =IF(E16>=0.99, D16*0.03, 0) | H16: =D16*0.03 | I16: =D16*0.0378 | J16: 0 | K16: =G16+H16+I16+J16 | L16: =K16*0.05 | M16: =K16+L16 | N16: =SUMIFS('Ajanta Credit Notes Log'!G:G, 'Ajanta Credit Notes Log'!B:B, "Jul-2027") | O16: =M16-N16
A17: TOTAL / YTD | B17: 12 Months | C17: =SUM(C5:C16) | D17: =SUM(D5:D16) | E17: =IF(C17>0, D17/C17, 0) | F17: =IF(E17>=0.99, "YTD Met", "Tracking") | G17: =SUM(G5:G16) | H17: =SUM(H5:H16) | I17: =SUM(I5:I16) | J17: =SUM(J5:J16) | K17: =SUM(K5:K16) | L17: =SUM(L5:L16) | M17: =SUM(M5:M16) | N17: =SUM(N5:N16) | O17: =SUM(O5:O16)

Sheet Quarterly & Annual (QTB-ATB)
A1: SKIL LIFESTYLE LLP — QUARTERLY TURNOVER BONUS (QTB) & ANNUAL BONUS (ATB)
A2: QTB: 2.00% on Quarterly Basic Turnover | ATB: 3.00% on Rs 1.20 Cr Annual Basic Target
A4: Period / Quarter | B4: Months Included | C4: Quarter Target (Basic Rs) | D4: Actual Basic Turnover (Rs) | E4: Quarter Achievement % | F4: Status | G4: QTB Rate (%) | H4: QTB Entitled Basic (Rs) | I4: Gross QTB with 5% IGST (Rs)
A5: Q2 (FY 26-27) | B5: Aug 2026 – Sep 2026 (2 Mo) | C5: 2000000 | D5: ='Monthly Target Tracker'!D5+'Monthly Target Tracker'!D6 | E5: =IF(C5>0, D5/C5, 0) | F5: =IF(D5=0, "Pending", IF(E5>=0.99, "Achieved", "Shortfall")) | G5: 0.02 | H5: =D5*G5 | I5: =H5*1.05
A6: Q3 (FY 26-27) | B6: Oct 2026 – Dec 2026 (3 Mo) | C6: 3000000 | D6: ='Monthly Target Tracker'!D7+'Monthly Target Tracker'!D8+'Monthly Target Tracker'!D9 | E6: =IF(C6>0, D6/C6, 0) | F6: =IF(D6=0, "Pending", IF(E6>=0.99, "Achieved", "Shortfall")) | G6: 0.02 | H6: =D6*G6 | I6: =H6*1.05
A7: Q4 (FY 26-27) | B7: Jan 2027 – Mar 2027 (3 Mo) | C7: 3000000 | D7: ='Monthly Target Tracker'!D10+'Monthly Target Tracker'!D11+'Monthly Target Tracker'!D12 | E7: =IF(C7>0, D7/C7, 0) | F7: =IF(D7=0, "Pending", IF(E7>=0.99, "Achieved", "Shortfall")) | G7: 0.02 | H7: =D7*G7 | I7: =H7*1.05
A8: Q1 (FY 27-28) | B8: Apr 2027 – Jul 2027 (4 Mo) | C8: 4000000 | D8: ='Monthly Target Tracker'!D13+'Monthly Target Tracker'!D14+'Monthly Target Tracker'!D15+'Monthly Target Tracker'!D16 | E8: =IF(C8>0, D8/C8, 0) | F8: =IF(D8=0, "Pending", IF(E8>=0.99, "Achieved", "Shortfall")) | G8: 0.02 | H8: =D8*G8 | I8: =H8*1.05
A9: TOTAL QUARTERLY | B9: 12 Months Total | C9: =SUM(C5:C8) | D9: =SUM(D5:D8) | E9: =IF(C9>0, D9/C9, 0) | F9: =IF(E9>=0.99, "Target Met", "In Progress") | G9: 2.00% Avg | H9: =SUM(H5:H8) | I9: =SUM(I5:I8)
A11: ANNUAL TURNOVER BONUS (ATB) AUDIT
A12: Annual Commitment Target (Basic) | B12: Contract Section 2.0 (Aug 2026 to Jul 2027) | C12: 12000000
A13: YTD Actual Basic Turnover Achieved | B13: Sum of 12 Months Basic Purchases from Ajanta | C13: =D9
A14: Annual Progress % | B14: =IF(C12>0, C13/C12, 0)
A15: Annual Turnover Bonus Rate (ATB) | B15: Contract Additional Bonus Clause 1 | C15: 0.03
A16: Projected Annual ATB Payout (Basic) | B16: =C13*C15
A17: Gross ATB with 5% IGST Credit Note | B17: =C16*1.05

Sheet Inward Bill Quick-Log
A1: SKIL LIFESTYLE LLP — COMPLETE INWARD PURCHASE INVOICE LOG (FY 2026–27)
A2: Audited & Verified Inward Supplies (Ajanta Shoes India Pvt. Ltd. & Xpania Footcare LLP) — 100% Reconciled to Tally Prime
A4: Vch # | B4: Invoice Number | C4: Supplier Trade Name | D4: Invoice Date | E4: Filing Month | F4: Customer / Consignee Name | G4: Basic Amount (Rs) | H4: Input IGST (Rs) | I4: Invoice Total (Rs) | J4: Tally Status | K4: Payment Terms | L4: CD Eligible?
A5: 1 | B5: 1900402723 | C5: Ajanta Shoes India Pvt. Ltd. | D5: 12/08/2026 | E5: Aug-2026 | F5: M/s Sri Brundabana Enterprises, Rayagada | G5: 41332.56 | H5: 2066.62 | I5: 43399 | J5: Verified in Tally | K5: On Account / 30D | L5: Yes
A6: 2 | B6: 1900402722 | C6: Ajanta Shoes India Pvt. Ltd. | D6: 12/08/2026 | E6: Aug-2026 | F6: Delight Footwear, Vizianagaram | G6: 145384.32 | H6: 7269.18 | I6: 152653.5 | J6: Verified in Tally | K6: On Account / 30D | L6: Yes
A7: 3 | B7: 1900402782 | C7: Ajanta Shoes India Pvt. Ltd. | D7: 12/08/2026 | E7: Aug-2026 | F7: M/s Sri Brundabana Enterprises, Rayagada | G7: 59077.92 | H7: 2953.88 | I7: 62032 | J7: Verified in Tally | K7: On Account / 30D | L7: Yes
A8: 4 | B8: 1900402692 | C8: Ajanta Shoes India Pvt. Ltd. | D8: 12/08/2026 | E8: Aug-2026 | F8: K G N Footware, Parvathipuram | G8: 49943.64 | H8: 2497.16 | I8: 52441 | J8: Verified in Tally | K8: On Account / 30D | L8: Yes
A9: 5 | B9: 1900402693 | C9: Ajanta Shoes India Pvt. Ltd. | D9: 12/08/2026 | E9: Aug-2026 | F9: K G N Footware, Parvathipuram | G9: 53376.3 | H9: 2668.83 | I9: 56045 | J9: Verified in Tally | K9: On Account / 30D | L9: Yes
A10: 6 | B10: 1900402694 | C10: Ajanta Shoes India Pvt. Ltd. | D10: 12/08/2026 | E10: Aug-2026 | F10: K G N Footware, Parvathipuram | G10: 5339.4 | H10: 266.97 | I10: 5606 | J10: Verified in Tally | K10: On Account / 30D | L10: Yes
A11: 7 | B11: 1900402797 | C11: Ajanta Shoes India Pvt. Ltd. | D11: 12/08/2026 | E11: Aug-2026 | F11: M/s Sri Brundabana Enterprises, Rayagada | G11: 80256.6 | H11: 4012.88 | I11: 84269 | J11: Verified in Tally | K11: On Account / 30D | L11: Yes
A12: 8 | B12: 1900402814 | C12: Ajanta Shoes India Pvt. Ltd. | D12: 12/08/2026 | E12: Aug-2026 | F12: M/s Sri Brundabana Enterprises, Rayagada | G12: 6053.7 | H12: 302.69 | I12: 6356 | J12: Verified in Tally | K12: On Account / 30D | L12: Yes
A13: 9 | B13: 1900402878 | C13: Ajanta Shoes India Pvt. Ltd. | D13: 12/08/2026 | E13: Aug-2026 | F13: M/s Sri Brundabana Enterprises, Rayagada | G13: 16018.5 | H13: 800.93 | I13: 16819 | J13: Verified in Tally | K13: On Account / 30D | L13: Yes
A14: 10 | B14: 1900402879 | C14: Ajanta Shoes India Pvt. Ltd. | D14: 12/08/2026 | E14: Aug-2026 | F14: M/s Sri Brundabana Enterprises, Rayagada | G14: 38448 | H14: 1922.42 | I14: 40370 | J14: Verified in Tally | K14: On Account / 30D | L14: Yes
A15: 11 | B15: 1900404091 | C15: Ajanta Shoes India Pvt. Ltd. | D15: 13/08/2026 | E15: Aug-2026 | F15: M/s. Shree Footwear, Srikakulam | G15: 67615.32 | H15: 3380.79 | I15: 70996 | J15: Verified in Tally | K15: On Account / 30D | L15: Yes
A16: 12 | B16: 1900404102 | C16: Ajanta Shoes India Pvt. Ltd. | D16: 13/08/2026 | E16: Aug-2026 | F16: M/s. Shree Footwear, Srikakulam | G16: 26222.76 | H16: 1311.15 | I16: 27534 | J16: Verified in Tally | K16: On Account / 30D | L16: Yes
... A61: 57 | B61: XPL/2369/26-27 | C61: XPANIA FOOTCARE LLP | D61: 12/10/2026 | E61: Oct-2026 | F61: SHREE ADITYA FOOT FASHION | G61: 13752 | H61: 687.6 | I61: 14440 | J61: Verified in Tally | K61: On Account / 30D | L61: N/A
A62: TOTAL | B62: 57 Bills | G62: =SUM(G5:G61) | H62: =SUM(H5:H61) | I62: =SUM(I5:I61) | J62: 100% VERIFIED

Sheet Ajanta Credit Notes Log
A1: SKIL LIFESTYLE LLP — AJANTA SHOES SETTLED CREDIT NOTES (CDNR) LOG
A2: Official Credit Notes from Ajanta Shoes (India) Pvt. Ltd. (GSTIN: 19AAECB6793N1ZV) Reconciled with Tally Debit Notes
A4: Credit Note # | B4: Filing Month | C4: Note Date | D4: Scheme / Incentive Category | E4: Taxable Basic (Rs) | F4: IGST 5% (Rs) | G4: Gross Note Value (Rs) | H4: Tally Debit Note Vch # | I4: Tally Entry Date | J4: Reconciliation Status
A5: 160005123 | B5: Aug-2026 | C5: 16/09/2026 | D5: 3.78% Retail Scheme (August 2026 Purchases) | E5: 43710.48 | F5: 2185.52 | G5: 45896 | H5: Debit Note #3 | I5: 16/09/2026 | J5: 100% Reconciled
A6: 160005126 | B6: Aug-2026 | C6: 16/09/2026 | D6: 3.00% Cash Discount (August Prompt Settlement) | E6: 35763.92 | F6: 1788.2 | G6: 37552.12 | H6: Debit Note #2 | I6: 16/09/2026 | J6: 100% Reconciled
A7: 160005127 | B7: Aug-2026 | C7: 16/09/2026 | D7: Rate Difference Rebate (UL 979E/CH+M Settlement) | E7: 2641.86 | F7: 132.09 | G7: 2773.95 | H7: Debit Note #4 | I7: 16/09/2026 | J7: 100% Reconciled
A8: 160005179 | B8: Aug-2026 | C8: 16/09/2026 | D8: Non-Bengal Scratch Coupon Scheme (Aug Promo) | E8: 24501.9 | F8: 1225.1 | G8: 25727 | H8: Debit Note #1 | I8: 16/09/2026 | J8: 100% Reconciled
A9: 160005562 | B9: Sep-2026 | C9: 30/09/2026 | D9: 2.00% QTB / Cash Discount (Sep 2026 Settlement) | E9: 19945.71 | F9: 997.29 | G9: 20943 | H9: Debit Note #7 | I9: 30/09/2026 | J9: 100% Reconciled
A10: 160005580 | B10: Sep-2026 | C10: 30/09/2026 | D10: Slab Scheme Bonus (Sep New State Target Bonus) | E10: 24933.33 | F10: 1246.67 | G10: 26180 | H10: Debit Note #6 | I10: 30/09/2026 | J10: 100% Reconciled
A11: 160005610 | B11: Sep-2026 | C11: 30/09/2026 | D11: 3.78% Retail Scheme (September 2026 Purchases) | E11: 37699.05 | F11: 1884.95 | G11: 39584 | H11: Debit Note #5 | I11: 30/09/2026 | J11: 100% Reconciled
A12: TOTAL | B12: 7 Notes | E12: =SUM(E5:E11) | F12: =SUM(F5:F11) | G12: =SUM(G5:G11) | J12: 100% MATCH
